ctREFPROP/__init__.py
ctREFPROP/ctREFPROP.py
ctREFPROP-0.10.4.dist-info/LICENSE.md
ctREFPROP-0.10.4.dist-info/METADATA
ctREFPROP-0.10.4.dist-info/WHEEL
ctREFPROP-0.10.4.dist-info/top_level.txt
ctREFPROP-0.10.4.dist-info/RECORD
