Metadata-Version: 2.1
Name: ctREFPROP
Version: 0.10.4
Summary: A ctypes wrapper for NIST REFPROP library
Author-email: Ian Bell <ian.bell@nist.gov>
Maintainer-email: Ian Bell <ian.bell@nist.gov>
License: # NIST Software Licensing Statement
Project-URL: Bug Reports, https://github.com/usnistgov/REFPROP-wrappers/issues
Project-URL: Source, https://github.com/usnistgov/REFPROP-wrappers
Classifier: Development Status :: 5 - Production/Stable
Classifier: Programming Language :: Python :: 3 :: Only
Requires-Python: >=3.8
License-File: LICENSE.md
